crack_pdf/__init__.py
crack_pdf/core.py
crack_pdf-0.1.1.dist-info/LICENSE
crack_pdf-0.1.1.dist-info/METADATA
crack_pdf-0.1.1.dist-info/WHEEL
crack_pdf-0.1.1.dist-info/entry_points.txt
crack_pdf-0.1.1.dist-info/top_level.txt
crack_pdf-0.1.1.dist-info/RECORD
