Metadata-Version: 2.1
Name: crack-pdf
Version: 0.1.1
Summary: A tool to crack password-protected PDFs
Home-page: https://github.com/szpatrichard/crack-pdf
Author: Richard Szilagyi
Author-email: szprichard@proton.me
Classifier: Programming Language :: Python :: 3
Classifier: License :: OSI Approved :: MIT License
Classifier: Operating System :: OS Independent
Requires-Python: >=3.6
License-File: LICENSE
Requires-Dist: PyPDF2
